semantha_sdk/__init__.py
semantha_sdk/administration/__init__.py
semantha_sdk/administration/administration.py
semantha_sdk/administration/administration_api.py
semantha_sdk/administration/domain.py
semantha_sdk/administration/domains.py
semantha_sdk/administration/model/error_field.py
semantha_sdk/administration/model/import_detail.py
semantha_sdk/administration/model/import_information.py
semantha_sdk/administration/model/role.py
semantha_sdk/administration/model/user.py
semantha_sdk/administration/model/user_create.py
semantha_sdk/administration/model/user_update.py
semantha_sdk/administration/roles.py
semantha_sdk/administration/transport.py
semantha_sdk/administration/user.py
semantha_sdk/administration/users.py
semantha_sdk/api/__init__.py
semantha_sdk/api/answers.py
semantha_sdk/api/bulk.py
semantha_sdk/api/bulk_domains.py
semantha_sdk/api/bulk_model.py
semantha_sdk/api/bulkdomains_documentclasses.py
semantha_sdk/api/bulkdomains_documenttypes.py
semantha_sdk/api/bulkdomains_domain.py
semantha_sdk/api/bulkdomains_referencedocuments.py
semantha_sdk/api/bulkdomains_references.py
semantha_sdk/api/bulkmodel_boostwords.py
semantha_sdk/api/bulkmodel_class.py
semantha_sdk/api/bulkmodel_classes.py
semantha_sdk/api/bulkmodel_dataproperties.py
semantha_sdk/api/bulkmodel_domain.py
semantha_sdk/api/bulkmodel_domains.py
semantha_sdk/api/bulkmodel_instances.py
semantha_sdk/api/bulkmodel_metadata.py
semantha_sdk/api/bulkmodel_namedentities.py
semantha_sdk/api/bulkmodel_rules.py
semantha_sdk/api/bulkmodel_stopwords.py
semantha_sdk/api/bulkmodel_synonyms.py
semantha_sdk/api/bulkmodelclass_instances.py
semantha_sdk/api/celltypes.py
semantha_sdk/api/chat.py
semantha_sdk/api/chats.py
semantha_sdk/api/child_extractorclasses.py
semantha_sdk/api/clone.py
semantha_sdk/api/conversions.py
semantha_sdk/api/currentuser.py
semantha_sdk/api/diff.py
semantha_sdk/api/docclass_customfields.py
semantha_sdk/api/docclass_documentclasses.py
semantha_sdk/api/docclass_referencedocuments.py
semantha_sdk-10.5.0.dist-info/LICENSE
semantha_sdk-10.5.0.dist-info/METADATA
semantha_sdk-10.5.0.dist-info/WHEEL
semantha_sdk-10.5.0.dist-info/RECORD
