Metadata-Version: 2.3
Name: semantha-sdk
Version: 10.5.0
Summary: This is a python client sdk for accessing semantha (the semantic platform)
License: Apache-2.0
Author: Sebastian Weigelt
Author-email: sebastian.weigelt@semantha.ai
Maintainer: semantha support
Maintainer-email: support@semantha.de
Requires-Python: >=3.10
Classifier: Programming Language :: Python :: 3
Classifier: License :: OSI Approved :: Apache Software License
Classifier: Operating System :: OS Independent
Requires-Dist: jproperties (>=2.1.1,<3.0.0)
Requires-Dist: marshmallow (>=4.0.0,<5.0.0)
Requires-Dist: marshmallow-dataclass (>=8.7,<9.0)
Requires-Dist: pyhumps (>=3.8.0,<4.0.0)
Requires-Dist: requests (>=2.32,<3.0)
Project-URL: Bug Tracker, https://github.com/semantha/semantha-python-client/issues
Project-URL: Homepage, https://github.com/semantha/semantha-python-client
